scope_classifier-0.3.1.dist-info/METADATA
scope_classifier-0.3.1.dist-info/WHEEL
scope_classifier-0.3.1.dist-info/entry_points.txt
scope_classifier-0.3.1.dist-info/licenses/LICENSE
scope_classifier/__init__.py
scope_classifier/classifiers/__init__.py
scope_classifier/classifiers/api.py
scope_classifier/classifiers/base.py
scope_classifier/classifiers/hf.py
scope_classifier/classifiers/vllm.py
scope_classifier/cli/__init__.py
scope_classifier/cli/main.py
scope_classifier/cli/serve.py
scope_classifier/modeling.py
scope_classifier/prompting.py
scope_classifier/serving/__init__.py
scope_classifier/serving/main.py
scope_classifier/serving/vllm_logging_config.json
scope_classifier-0.3.1.dist-info/RECORD
