Metadata-Version: 2.1
Name: scope-classifier
Version: 0.3.1
Summary: A scope classification library around your prompts
Author-Email: Luigi Procopio <luigi@principled-intelligence.com>, Edoardo Barba <edoardo@principled-intelligence.com>
License: Apache-2.0
Requires-Python: >=3.10
Requires-Dist: pydantic>=2.0.0
Requires-Dist: typer>=0.12.3
Requires-Dist: requests
Requires-Dist: aiohttp
Provides-Extra: hf
Requires-Dist: transformers<5.0.0,>=4.47.0; extra == "hf"
Requires-Dist: accelerate>=1.11.0; extra == "hf"
Provides-Extra: vllm
Requires-Dist: transformers<5.0.0,>=4.47.0; extra == "vllm"
Requires-Dist: vllm>=0.11.0; extra == "vllm"
Provides-Extra: serve
Requires-Dist: scope-classifier[serve]; extra == "serve"
Requires-Dist: fastapi[standard]>=0.119.1; extra == "serve"
Requires-Dist: uvicorn>=0.29.0; extra == "serve"
Requires-Dist: vllm>=0.11.0; extra == "serve"
